{
  "id": "reference/plan/plan-reference",
  "title": "PLAN",
  "description": "Reference for implementing a PLAN interpreter",
  "source": "@site/../../doc/reference/plan/plan.md",
  "sourceDirName": "reference/plan",
  "slug": "/reference/plan/",
  "permalink": "/reference/plan/",
  "draft": false,
  "unlisted": false,
  "editUrl": "https://github.com/operating-function/pallas/edit/main/doc/../../doc/reference/plan/plan.md",
  "tags": [],
  "version": "current",
  "frontMatter": {
    "id": "plan-reference",
    "title": "PLAN"
  },
  "sidebar": "referenceSidebar",
  "previous": {
    "title": "Effects Reference",
    "permalink": "/reference/vm-and-interpreter/effects-reference"
  }
}